[
    {
        "code": 200,
        "message": "OK",
        "data": {
            "total": 22,
            "questions": [
                {
                    "id": 12841,
                    "subject_id": 3,
                    "chapter_id": 265,
                    "question_id": "12ab74f7-d923-45f0-9204-a874ac4434c8",
                    "difficulty": "Easy",
                    "answer": "1",
                    "question_type": 1,
                    "question": "хЗВчЅ $P(A)+P(B)=0.8, P(A B)=0.3$, х?$A, B$ щНфИхччцІчфИК ( ).",
                    "analysis": "ц ЙцЎхЏЙхЖхО?$\\bar{A} \\bar{B}=\\overline{A \\cup B}$, х\n$$\nP(\\bar{A} \\bar{B})=1-P(A \\cup B)=1-[P(A)+P(B)-P(A B)]=0.5 .\n$$",
                    "question_render_type": 1,
                    "analysis_render_type": 1,
                    "created_at": {
                        "seconds": 1764250432
                    },
                    "question_json": "mathreact/72c015cb2c2044159d54689ce6d26514",
                    "updated_at": {
                        "seconds": 1775673120
                    },
                    "version": 2,
                    "is_active_version": true,
                    "choices": [
                        {
                            "id": 51361,
                            "question_id": 12841,
                            "is_answer": true,
                            "choice": "$0.5$",
                            "choice_render_type": 1,
                            "choice_id": "1",
                            "created_at": {
                                "seconds": 1735080681
                            },
                            "updated_at": {
                                "seconds": 1735080681
                            }
                        },
                        {
                            "id": 51363,
                            "question_id": 12841,
                            "is_answer": false,
                            "choice": "$0.6$",
                            "choice_render_type": 1,
                            "choice_id": "2",
                            "created_at": {
                                "seconds": 1735080681
                            },
                            "updated_at": {
                                "seconds": 1735080681
                            }
                        },
                        {
                            "id": 51362,
                            "question_id": 12841,
                            "is_answer": false,
                            "choice": "$0.8$",
                            "choice_render_type": 1,
                            "choice_id": "3",
                            "created_at": {
                                "seconds": 1735080681
                            },
                            "updated_at": {
                                "seconds": 1735080681
                            }
                        },
                        {
                            "id": 51364,
                            "question_id": 12841,
                            "is_answer": false,
                            "choice": "$0.3$",
                            "choice_render_type": 1,
                            "choice_id": "4",
                            "created_at": {
                                "seconds": 1735080681
                            },
                            "updated_at": {
                                "seconds": 1735080681
                            }
                        }
                    ],
                    "accuracy_rate": 0.96,
                    "difficulty_score": 0.19,
                    "avg_time_spent": 367790,
                    "tags": "",
                    "ai_tags": "цІч,х цГхЌхМ,хЏЙхЖхО?
                },
                {
                    "id": 12845,
                    "subject_id": 3,
                    "chapter_id": 265,
                    "question_id": "0bbd78b4-6e40-414a-94d3-a4530baf808e",
                    "difficulty": "Easy",
                    "answer": "1",
                    "question_type": 1,
                    "question": "шЎ?$A, B$ фИКщцКфКфЛ? $P(A)=0.7, P(B)=0.5, P(A-B)=0.3$, х?(1) $P(A B)=()$, (2) $P(B-A)=()$.",
                    "analysis": "(1) ч?$P(A-B)=P(A-A B)=P(A)-P(A B)=0.7-P(A B)=0.3$, х?$P(A B)=0.4$;\n(2) $P(B-A)=P(B)-P(A B)=0.5-0.4=0.1$.",
                    "question_render_type": 1,
                    "analysis_render_type": 1,
                    "created_at": {
                        "seconds": 1764250432
                    },
                    "question_json": "mathreact/c71e4f2db12b49eab27048d51e3c1c75",
                    "updated_at": {
                        "seconds": 1775673115
                    },
                    "version": 2,
                    "is_active_version": true,
                    "choices": [
                        {
                            "id": 51379,
                            "question_id": 12845,
                            "is_answer": true,
                            "choice": "$0.4,0.1$",
                            "choice_render_type": 1,
                            "choice_id": "1",
                            "created_at": {
                                "seconds": 1735080681
                            },
                            "updated_at": {
                                "seconds": 1735080681
                            }
                        },
                        {
                            "id": 51380,
                            "question_id": 12845,
                            "is_answer": false,
                            "choice": "$0.6,0.2$",
                            "choice_render_type": 1,
                            "choice_id": "2",
                            "created_at": {
                                "seconds": 1735080681
                            },
                            "updated_at": {
                                "seconds": 1735080681
                            }
                        },
                        {
                            "id": 51378,
                            "question_id": 12845,
                            "is_answer": false,
                            "choice": "$0.4,0.2$",
                            "choice_render_type": 1,
                            "choice_id": "3",
                            "created_at": {
                                "seconds": 1735080681
                            },
                            "updated_at": {
                                "seconds": 1735080681
                            }
                        },
                        {
                            "id": 51377,
                            "question_id": 12845,
                            "is_answer": false,
                            "choice": "$0.5,0.2$",
                            "choice_render_type": 1,
                            "choice_id": "4",
                            "created_at": {
                                "seconds": 1735080681
                            },
                            "updated_at": {
                                "seconds": 1735080681
                            }
                        }
                    ],
                    "accuracy_rate": 0.88,
                    "difficulty_score": 0.29,
                    "avg_time_spent": 95482,
                    "tags": "шПццщ,шПц69фККхщ?,
                    "ai_tags": "щцКфКфЛЖ,цІчшЎЁчЎ,хЗЎфКфЛ?
                },
                {
                    "id": 12846,
                    "subject_id": 3,
                    "chapter_id": 265,
                    "question_id": "1b025dbe-b5d3-4616-bf5e-73e611358c29",
                    "difficulty": "Easy",
                    "answer": "1",
                    "question_type": 1,
                    "question": "шЎ?$A, B$ цЏфИЄфКфЛЖфИ?$P(A)=0.6, P(B)=0.7$, хН?$P(A B)$ ххАцхЄЇхМцЖц?( ), хН?$P(A B)$ ххАцхАхМцЏ ( ).",
                    "analysis": "ч?$A, B$ фИЄфКфЛЖцІчч, $A, B$ фКфКфЛЖчИхЎ? хЉчЈх цГхЌхМц\n$$\nP(A B)=P(A)+P(B)-P(A \\cup B) .\n$$\n(1) ч?$P(B)=0.7, P(A)=0.6$, ч?$P(B)>P(A)$.\n\nхН?$B \\supset A$ ц? $A B=A, A \\cup B=B, P(A \\cup B)=P(B)$ фИКцхА? ц­ЄцЖ, $P(A B)$ фИКцхЄ? ц\n$$\n\\left.P(A B)\\right|_{\\max }=P(A)=0.6 .\n$$\n(2) х фИК $P(B) \\leq P(A \\cup B) \\leq 1$, цхН $P(A \\cup B)=1$ ц? $P(A B)$ цхА? фИ\n$$\n\\left.P(A B)\\right|_{\\min }=P(A)+P(B)-1=0.6+0.7-1=0.3 .\n$$",
                    "question_render_type": 1,
                    "analysis_render_type": 1,
                    "created_at": {
                        "seconds": 1764250432
                    },
                    "question_json": "mathreact/18e71ff913464646a488ff364488af0a",
                    "updated_at": {
                        "seconds": 1775673118
                    },
                    "version": 2,
                    "is_active_version": true,
                    "choices": [
                        {
                            "id": 51381,
                            "question_id": 12846,
                            "is_answer": true,
                            "choice": "$\\left.P(A B)\\right|_{\\max }=0.6 ;\\left.\\quad P(A B)\\right|_{\\min }=0.3$",
                            "choice_render_type": 1,
                            "choice_id": "1",
                            "created_at": {
                                "seconds": 1735080681
                            },
                            "updated_at": {
                                "seconds": 1735080681
                            }
                        },
                        {
                            "id": 51382,
                            "question_id": 12846,
                            "is_answer": false,
                            "choice": "$\\left.P(A B)\\right|_{\\max }=0.5 ;\\left.\\quad P(A B)\\right|_{\\min }=0.3$",
                            "choice_render_type": 1,
                            "choice_id": "2",
                            "created_at": {
                                "seconds": 1735080681
                            },
                            "updated_at": {
                                "seconds": 1735080681
                            }
                        },
                        {
                            "id": 51383,
                            "question_id": 12846,
                            "is_answer": false,
                            "choice": "$\\left.P(A B)\\right|_{\\max }=0.6 ;\\left.\\quad P(A B)\\right|_{\\min }=0.2$",
                            "choice_render_type": 1,
                            "choice_id": "3",
                            "created_at": {
                                "seconds": 1735080681
                            },
                            "updated_at": {
                                "seconds": 1735080681
                            }
                        },
                        {
                            "id": 51384,
                            "question_id": 12846,
                            "is_answer": false,
                            "choice": "$\\left.P(A B)\\right|_{\\max }=0.5 ;\\left.\\quad P(A B)\\right|_{\\min }=0.4$",
                            "choice_render_type": 1,
                            "choice_id": "4",
                            "created_at": {
                                "seconds": 1735080681
                            },
                            "updated_at": {
                                "seconds": 1735080681
                            }
                        }
                    ],
                    "accuracy_rate": 0.91,
                    "difficulty_score": 0.28,
                    "avg_time_spent": 182578,
                    "tags": "шПц48фККхщ?,
                    "ai_tags": "цІччхКцЌцЇшДЈ,х цГхЌхМ"
                },
                {
                    "id": 12848,
                    "subject_id": 3,
                    "chapter_id": 265,
                    "question_id": "ff0af89e-cfd0-436b-9bb8-2cfc26f356ac",
                    "difficulty": "Easy",
                    "answer": "1",
                    "question_type": 1,
                    "question": "хЗВчЅфКфЛЖ $A \\subset B, P(A)=0.2, P(B)=0.3$, х?$P(B \\bar{A})=()$.",
                    "analysis": "чБфК $A \\subset B$, цфЛЅц ЙцЎцІччцЇшДЈц?$P(B \\bar{A})=P(B-A)=P(B)-P(A)=0.3-0.2=0.1$.",
                    "question_render_type": 1,
                    "analysis_render_type": 1,
                    "created_at": {
                        "seconds": 1764250432
                    },
                    "question_json": "mathreact/e15b7eb07f40475a954ed2f242b2b4a1",
                    "updated_at": {
                        "seconds": 1775673114
                    },
                    "version": 2,
                    "is_active_version": true,
                    "choices": [
                        {
                            "id": 51390,
                            "question_id": 12848,
                            "is_answer": true,
                            "choice": "$0.1$",
                            "choice_render_type": 1,
                            "choice_id": "1",
                            "created_at": {
                                "seconds": 1735080681
                            },
                            "updated_at": {
                                "seconds": 1735080681
                            }
                        },
                        {
                            "id": 51392,
                            "question_id": 12848,
                            "is_answer": false,
                            "choice": "$0.2$",
                            "choice_render_type": 1,
                            "choice_id": "2",
                            "created_at": {
                                "seconds": 1735080681
                            },
                            "updated_at": {
                                "seconds": 1735080681
                            }
                        },
                        {
                            "id": 51391,
                            "question_id": 12848,
                            "is_answer": false,
                            "choice": "$0.3$",
                            "choice_render_type": 1,
                            "choice_id": "3",
                            "created_at": {
                                "seconds": 1735080681
                            },
                            "updated_at": {
                                "seconds": 1735080681
                            }
                        },
                        {
                            "id": 51389,
                            "question_id": 12848,
                            "is_answer": false,
                            "choice": "$0.4$",
                            "choice_render_type": 1,
                            "choice_id": "4",
                            "created_at": {
                                "seconds": 1735080681
                            },
                            "updated_at": {
                                "seconds": 1735080681
                            }
                        }
                    ],
                    "accuracy_rate": 0.95,
                    "difficulty_score": 0.2,
                    "avg_time_spent": 100547,
                    "tags": "",
                    "ai_tags": "цІччхКцЌцЇшДЈ,фКфЛЖчшПчЎ?
                },
                {
                    "id": 12849,
                    "subject_id": 3,
                    "chapter_id": 265,
                    "question_id": "83f9e2bf-a925-4bb1-be2f-dbeb065ac63f",
                    "difficulty": "Easy",
                    "answer": "1",
                    "question_type": 1,
                    "question": "хЗВчЅ $P(A)=0.5, P(B)=0.4, P(A \\cup B)=0.7$, х?$P(A-B)=()$.",
                    "analysis": "чБфК $P(A \\cup B)=P(A)+P(B)-P(A B)$,\nцфЛ?$P(A B)=P(A)+P(B)-P(A \\cup B)=0.5+0.4-0.7=0.2$,\nх?$P(A-B)=P(A)-P(A B)=0.5-0.2=0.3$.",
                    "question_render_type": 1,
                    "analysis_render_type": 1,
                    "created_at": {
                        "seconds": 1764250432
                    },
                    "question_json": "mathreact/2733c93ef79743a9821311ac6ddbde32",
                    "updated_at": {
                        "seconds": 1775673118
                    },
                    "version": 2,
                    "is_active_version": true,
                    "choices": [
                        {
                            "id": 51394,
                            "question_id": 12849,
                            "is_answer": true,
                            "choice": "$0.3$",
                            "choice_render_type": 1,
                            "choice_id": "1",
                            "created_at": {
                                "seconds": 1735080681
                            },
                            "updated_at": {
                                "seconds": 1735080681
                            }
                        },
                        {
                            "id": 51396,
                            "question_id": 12849,
                            "is_answer": false,
                            "choice": "$0.4$",
                            "choice_render_type": 1,
                            "choice_id": "2",
                            "created_at": {
                                "seconds": 1735080681
                            },
                            "updated_at": {
                                "seconds": 1735080681
                            }
                        },
                        {
                            "id": 51395,
                            "question_id": 12849,
                            "is_answer": false,
                            "choice": "$0.5$",
                            "choice_render_type": 1,
                            "choice_id": "3",
                            "created_at": {
                                "seconds": 1735080681
                            },
                            "updated_at": {
                                "seconds": 1735080681
                            }
                        },
                        {
                            "id": 51393,
                            "question_id": 12849,
                            "is_answer": false,
                            "choice": "$0.7$",
                            "choice_render_type": 1,
                            "choice_id": "4",
                            "created_at": {
                                "seconds": 1735080681
                            },
                            "updated_at": {
                                "seconds": 1735080681
                            }
                        }
                    ],
                    "accuracy_rate": 0.97,
                    "difficulty_score": 0.23,
                    "avg_time_spent": 90616,
                    "ai_tags": "цІччхКцЌцЇшДЈ,х цГхЌхМ"
                },
                {
                    "id": 12851,
                    "subject_id": 3,
                    "chapter_id": 265,
                    "question_id": "fb504f27-15d0-485a-add3-bf6f42fd3273",
                    "difficulty": "Easy",
                    "answer": "1",
                    "question_type": 1,
                    "question": "$A, B$ чИфКчЌчЋ, $P(A)=0.75, P(A-B)=0.45$, х?$P(B)=()$.",
                    "analysis": "чБфК $A, B$ чИфКчЌчЋ, цфЛ?$P(A B)=P(A) P(B)$,хчБцІччцЇшДЈхО?$P(A-B)=P(A)-P(A B)=P(A)-P(A) P(B)$,х?$0.45=0.75-0.75 \\cdot P(B)$, цфЛ?$P(B)=0.4$.",
                    "question_render_type": 1,
                    "analysis_render_type": 1,
                    "created_at": {
                        "seconds": 1764250432
                    },
                    "question_json": "mathreact/56f205804c784f86a051860330e4d68f",
                    "updated_at": {
                        "seconds": 1775673120
                    },
                    "version": 2,
                    "is_active_version": true,
                    "choices": [
                        {
                            "id": 51402,
                            "question_id": 12851,
                            "is_answer": true,
                            "choice": "$0.4$",
                            "choice_render_type": 1,
                            "choice_id": "1",
                            "created_at": {
                                "seconds": 1735080681
                            },
                            "updated_at": {
                                "seconds": 1735080681
                            }
                        },
                        {
                            "id": 51404,
                            "question_id": 12851,
                            "is_answer": false,
                            "choice": "$0.3$",
                            "choice_render_type": 1,
                            "choice_id": "2",
                            "created_at": {
                                "seconds": 1735080681
                            },
                            "updated_at": {
                                "seconds": 1735080681
                            }
                        },
                        {
                            "id": 51401,
                            "question_id": 12851,
                            "is_answer": false,
                            "choice": "$0.3375$",
                            "choice_render_type": 1,
                            "choice_id": "3",
                            "created_at": {
                                "seconds": 1735080681
                            },
                            "updated_at": {
                                "seconds": 1735080681
                            }
                        },
                        {
                            "id": 51403,
                            "question_id": 12851,
                            "is_answer": false,
                            "choice": "$0.85$",
                            "choice_render_type": 1,
                            "choice_id": "4",
                            "created_at": {
                                "seconds": 1735080681
                            },
                            "updated_at": {
                                "seconds": 1735080681
                            }
                        }
                    ],
                    "accuracy_rate": 0.74,
                    "difficulty_score": 0.29,
                    "avg_time_spent": 93609,
                    "tags": "шПццщ,шПц134фККхщ?,
                    "ai_tags": "фКфЛЖччЌчЋц?цІччхКцЌцЇшДЈ"
                },
                {
                    "id": 12853,
                    "subject_id": 3,
                    "chapter_id": 265,
                    "question_id": "34c83f81-987e-4223-8762-de812f074cbc",
                    "difficulty": "Easy",
                    "answer": "1",
                    "question_type": 1,
                    "question": "шЎ?$P(A)=a, P(B)=b, P(A+B)=c$, х?$P(A \\bar{B})$ фИ?$($ ).",
                    "analysis": "чБцІччцЇшДЈхО?$P(A+B)=P(A)+P(B)-P(A B)$, цфЛ?$P(A B)=a+b-c$.хц $P(A)=P(A B+A \\bar{B})$, х?$P(A)=P(A B)+P(A \\bar{B})$,цфЛ?$P(A \\bar{B})=P(A)-P(A B)=a-(a+b-c)=c-b$.",
                    "question_render_type": 1,
                    "analysis_render_type": 1,
                    "created_at": {
                        "seconds": 1764250432
                    },
                    "question_json": "mathreact/bddc65b6422f421bbe1e9801015f83d5",
                    "updated_at": {
                        "seconds": 1775673116
                    },
                    "version": 2,
                    "is_active_version": true,
                    "choices": [
                        {
                            "id": 51412,
                            "question_id": 12853,
                            "is_answer": true,
                            "choice": "$c-b$",
                            "choice_render_type": 1,
                            "choice_id": "1",
                            "created_at": {
                                "seconds": 1735080681
                            },
                            "updated_at": {
                                "seconds": 1735080681
                            }
                        },
                        {
                            "id": 51409,
                            "question_id": 12853,
                            "is_answer": false,
                            "choice": "$a-b$",
                            "choice_render_type": 1,
                            "choice_id": "2",
                            "created_at": {
                                "seconds": 1735080681
                            },
                            "updated_at": {
                                "seconds": 1735080681
                            }
                        },
                        {
                            "id": 51411,
                            "question_id": 12853,
                            "is_answer": false,
                            "choice": "$a(1-b)$",
                            "choice_render_type": 1,
                            "choice_id": "3",
                            "created_at": {
                                "seconds": 1735080681
                            },
                            "updated_at": {
                                "seconds": 1735080681
                            }
                        },
                        {
                            "id": 51410,
                            "question_id": 12853,
                            "is_answer": false,
                            "choice": "$b-a$",
                            "choice_render_type": 1,
                            "choice_id": "4",
                            "created_at": {
                                "seconds": 1735080681
                            },
                            "updated_at": {
                                "seconds": 1735080681
                            }
                        }
                    ],
                    "accuracy_rate": 0.93,
                    "difficulty_score": 0.23,
                    "avg_time_spent": 349068,
                    "tags": "шПц40фККхщ?,
                    "ai_tags": "цІчшЎ?щцКфКфЛЖ,х цГхЌхМ"
                },
                {
                    "id": 12856,
                    "subject_id": 3,
                    "chapter_id": 265,
                    "question_id": "19b9d220-1ead-4f82-817b-c06d5abdb608",
                    "difficulty": "Easy",
                    "answer": "1",
                    "question_type": 1,
                    "question": "шЎ?$P(A)=\\frac{1}{3}, P(B)=\\frac{1}{4}, P(A \\cup B)=\\frac{1}{2}$, х?$P(\\bar{A} \\cup \\bar{B})=()$.",
                    "analysis": "$P(\\bar{A} \\cup \\bar{B})=P(\\overline{A B})=1-P(A B)=1-[P(A)+P(B)-P(A \\cup B)]=\\frac{11}{12}$.",
                    "question_render_type": 1,
                    "analysis_render_type": 1,
                    "created_at": {
                        "seconds": 1764250432
                    },
                    "question_json": "mathreact/b9c991875f0b4eda99068e6ac847f9f0",
                    "updated_at": {
                        "seconds": 1775673113
                    },
                    "version": 2,
                    "is_active_version": true,
                    "choices": [
                        {
                            "id": 51421,
                            "question_id": 12856,
                            "is_answer": true,
                            "choice": "$\\frac{11}{12}$",
                            "choice_render_type": 1,
                            "choice_id": "1",
                            "created_at": {
                                "seconds": 1735080681
                            },
                            "updated_at": {
                                "seconds": 1735080681
                            }
                        },
                        {
                            "id": 51423,
                            "question_id": 12856,
                            "is_answer": false,
                            "choice": "$1$",
                            "choice_render_type": 1,
                            "choice_id": "2",
                            "created_at": {
                                "seconds": 1735080681
                            },
                            "updated_at": {
                                "seconds": 1735080681
                            }
                        },
                        {
                            "id": 51424,
                            "question_id": 12856,
                            "is_answer": false,
                            "choice": "$\\frac{5}{6}$",
                            "choice_render_type": 1,
                            "choice_id": "3",
                            "created_at": {
                                "seconds": 1735080681
                            },
                            "updated_at": {
                                "seconds": 1735080681
                            }
                        },
                        {
                            "id": 51422,
                            "question_id": 12856,
                            "is_answer": false,
                            "choice": "$\\frac{3}{4}$",
                            "choice_render_type": 1,
                            "choice_id": "4",
                            "created_at": {
                                "seconds": 1735080681
                            },
                            "updated_at": {
                                "seconds": 1735080681
                            }
                        }
                    ],
                    "accuracy_rate": 0.95,
                    "difficulty_score": 0.25,
                    "avg_time_spent": 139684,
                    "tags": "",
                    "ai_tags": "цІчшЎ?цІччхКцЌцЇшДЈ,х цГхЌхМ"
                },
                {
                    "id": 12858,
                    "subject_id": 3,
                    "chapter_id": 265,
                    "question_id": "8e36d706-d141-4333-a207-2a96460a457c",
                    "difficulty": "Easy",
                    "answer": "1",
                    "question_type": 1,
                    "question": "щцКфКфЛЖ $A, B$ фКцЅ, $P(A)=p, P(B)=q$, х?$P(\\bar{A} \\cup B)=()$.",
                    "analysis": "чБфКфКфЛЖ $A, B$ фКцЅ, цфЛ?$B \\subset \\bar{A}$ (чЈхОчЄКцГхОхЎЙцчхКцЅ, шЇфИх?\n\nцфЛ?$P(\\bar{A} \\cup B)=P(\\bar{A})=1-P(A)=1-p$.",
                    "question_render_type": 1,
                    "analysis_render_type": 1,
                    "created_at": {
                        "seconds": 1764250432
                    },
                    "question_json": "mathreact/17ebc0cd10434cf18d4a3ba809924a19",
                    "updated_at": {
                        "seconds": 1775673118
                    },
                    "version": 2,
                    "is_active_version": true,
                    "choices": [
                        {
                            "id": 51432,
                            "question_id": 12858,
                            "is_answer": true,
                            "choice": "$1-p$",
                            "choice_render_type": 1,
                            "choice_id": "1",
                            "created_at": {
                                "seconds": 1735080681
                            },
                            "updated_at": {
                                "seconds": 1735080681
                            }
                        },
                        {
                            "id": 51429,
                            "question_id": 12858,
                            "is_answer": false,
                            "choice": "$p$",
                            "choice_render_type": 1,
                            "choice_id": "2",
                            "created_at": {
                                "seconds": 1735080681
                            },
                            "updated_at": {
                                "seconds": 1735080681
                            }
                        },
                        {
                            "id": 51431,
                            "question_id": 12858,
                            "is_answer": false,
                            "choice": "$1-q$",
                            "choice_render_type": 1,
                            "choice_id": "3",
                            "created_at": {
                                "seconds": 1735080681
                            },
                            "updated_at": {
                                "seconds": 1735080681
                            }
                        },
                        {
                            "id": 51430,
                            "question_id": 12858,
                            "is_answer": false,
                            "choice": "$q$",
                            "choice_render_type": 1,
                            "choice_id": "4",
                            "created_at": {
                                "seconds": 1735080681
                            },
                            "updated_at": {
                                "seconds": 1735080681
                            }
                        }
                    ],
                    "accuracy_rate": 0.8,
                    "difficulty_score": 0.29,
                    "avg_time_spent": 83871,
                    "tags": "шПццщ,шПц113фККхщ?,
                    "ai_tags": "цІчшЎ?фКцЅфКфЛЖ,цІчцЇшДЈ"
                },
                {
                    "id": 12859,
                    "subject_id": 3,
                    "chapter_id": 265,
                    "question_id": "e7ccff84-c001-4550-b32d-bc9d39d934f5",
                    "difficulty": "Easy",
                    "answer": "1",
                    "question_type": 1,
                    "question": "ш?$P(A)=0.5, P(B)=0.4, P(A-B)=0.3$, цБ?$P(A \\cup B)=() у?P(\\bar{A} \\cup \\bar{B})=()$.",
                    "analysis": "шЇЃцГфИ х фИК $P(A-B)=0.3>P(A)-P(B)=0.1$, х?$P(A-B)<P(A)$, шПшЏДц?$A$ фИ?$B$ цЂфИчИфКц? хц ххЋхГчГЛ, шцЏфИшЌччИхЎЙхГчГЛ. х ц­Єх цГхЌхМ, ц\n$$\nP(A \\cup B)=P(A)+P(B)-P(A B),\n$$\n\nхчБ $P(A-B)=P(A-A B)=P(A)-P(A B)$, цхО\n$$\nP(A B)=P(A)-P(A-B)=0.5-0.3=0.2,\n$$\n\nцфЛЅ\n$$\n\\begin{aligned}\n& P(A \\cup B)=0.5+0.4-0.2=0.7, \\text { ш?} \\\\\n& P(\\bar{A} \\cup \\bar{B})=P(\\overline{A B})=1-P(A B)=1-0.2=0.8 .\n\\end{aligned}\n$$\n\nшЇЃцГфК?чБфК $A$ фИ?$B$ чИхЎЙ, х ц­Є $A \\cup B$ хЏхфИ?$B \\cup(A-B), B$ фИ?$A-B$ фКцЅ, фЛш\n$$\n\\begin{aligned}\n& P(A \\cup B)=P(B \\cup(A-B))=P(B)+P(A-B)=0.4+0.3=0.7 \\\\\n& A=A(B \\cup \\bar{B})=A B \\cup A \\bar{B}, \\\\\n& P(A)=P(A B)+P(A \\bar{B})=P(A B)+P(A-B),\n\\end{aligned}\n$$\n\nцфЛ?$P(A B)=P(A)-P(A-B)=0.5-0.3=0.2$, фКцЏ\n$$\nP(\\bar{A} \\cup \\bar{B})=P(\\overline{A B})=1-P(A B)=1-0.2=0.8 .\n$$",
                    "question_render_type": 1,
                    "analysis_render_type": 1,
                    "created_at": {
                        "seconds": 1764250432
                    },
                    "question_json": "mathreact/5c82192f5d754b8a9f2bfe8ded2f11da",
                    "updated_at": {
                        "seconds": 1775673115
                    },
                    "version": 2,
                    "is_active_version": true,
                    "choices": [
                        {
                            "id": 51434,
                            "question_id": 12859,
                            "is_answer": true,
                            "choice": "$0.7 ; \\quad 0.8$",
                            "choice_render_type": 1,
                            "choice_id": "1",
                            "created_at": {
                                "seconds": 1735080681
                            },
                            "updated_at": {
                                "seconds": 1735080681
                            }
                        },
                        {
                            "id": 51435,
                            "question_id": 12859,
                            "is_answer": false,
                            "choice": "$0.4 ; \\quad 0.8$",
                            "choice_render_type": 1,
                            "choice_id": "2",
                            "created_at": {
                                "seconds": 1735080681
                            },
                            "updated_at": {
                                "seconds": 1735080681
                            }
                        },
                        {
                            "id": 51436,
                            "question_id": 12859,
                            "is_answer": false,
                            "choice": "$0.5 ; \\quad 0.9$",
                            "choice_render_type": 1,
                            "choice_id": "3",
                            "created_at": {
                                "seconds": 1735080681
                            },
                            "updated_at": {
                                "seconds": 1735080681
                            }
                        },
                        {
                            "id": 51433,
                            "question_id": 12859,
                            "is_answer": false,
                            "choice": "$0.1 ; \\quad 1.0$",
                            "choice_render_type": 1,
                            "choice_id": "4",
                            "created_at": {
                                "seconds": 1735080681
                            },
                            "updated_at": {
                                "seconds": 1735080681
                            }
                        }
                    ],
                    "accuracy_rate": 0.97,
                    "difficulty_score": 0.24,
                    "avg_time_spent": 106129,
                    "tags": "",
                    "ai_tags": "цІччхКцЌцЇшДЈ,х цГхЌхМ"
                }
            ]
        }
    },
    {
        "code": 200,
        "message": "OK",
        "data": {
            "total": 22,
            "questions": [
                {
                    "id": 12861,
                    "subject_id": 3,
                    "chapter_id": 265,
                    "question_id": "e109846e-fcb5-4311-9f22-69f6cdaac183",
                    "difficulty": "Easy",
                    "answer": "1",
                    "question_type": 1,
                    "question": "шЎ?$A, B$ фКфИчИхЎЙ, фИ?$P(A)=p, P(B)=q$, х?$P((\\bar{A} \\cup B) \\cap(A \\cup \\bar{B}))=()$.",
                    "analysis": "ххчЎ $(\\bar{A} \\cup B) \\cap(A \\cup \\bar{B})$, ц\n$$\n\\begin{aligned}\n&(\\bar{A} \\cup B) \\cap(A \\cup \\bar{B})=\\bar{A} \\cdot \\bar{B} \\cup A B, \\\\\n& \\text { фКцЏ } P((\\bar{A} \\cup B) \\cap(A \\cup \\bar{B}))=P(\\bar{A} \\cdot \\bar{B} \\cup A B) \\\\\n&=P(\\bar{A} \\cdot \\bar{B})+P(A B)-P(\\bar{A} \\cdot \\bar{B} A B) \\\\\n&=P(\\overline{A \\cup B})+0-0=1-P(A \\cup B) \\\\\n&=1-[P(A)+P(B)-P(A B)] \\\\\n&=1-(p+q-0)=1-(p+q) .\n\\end{aligned}\n$$",
                    "question_render_type": 1,
                    "analysis_render_type": 1,
                    "created_at": {
                        "seconds": 1764250432
                    },
                    "question_json": "mathreact/65de312d84b947e7b28ad9ca8a668c83",
                    "updated_at": {
                        "seconds": 1775673118
                    },
                    "version": 2,
                    "is_active_version": true,
                    "choices": [
                        {
                            "id": 51443,
                            "question_id": 12861,
                            "is_answer": true,
                            "choice": "$1-(p+q)$",
                            "choice_render_type": 1,
                            "choice_id": "1",
                            "created_at": {
                                "seconds": 1735080681
                            },
                            "updated_at": {
                                "seconds": 1735080681
                            }
                        },
                        {
                            "id": 51441,
                            "question_id": 12861,
                            "is_answer": false,
                            "choice": "$p+q-p q$",
                            "choice_render_type": 1,
                            "choice_id": "2",
                            "created_at": {
                                "seconds": 1735080681
                            },
                            "updated_at": {
                                "seconds": 1735080681
                            }
                        },
                        {
                            "id": 51442,
                            "question_id": 12861,
                            "is_answer": false,
                            "choice": "$1-q$",
                            "choice_render_type": 1,
                            "choice_id": "3",
                            "created_at": {
                                "seconds": 1735080681
                            },
                            "updated_at": {
                                "seconds": 1735080681
                            }
                        },
                        {
                            "id": 51444,
                            "question_id": 12861,
                            "is_answer": false,
                            "choice": "$1-p$",
                            "choice_render_type": 1,
                            "choice_id": "4",
                            "created_at": {
                                "seconds": 1735080681
                            },
                            "updated_at": {
                                "seconds": 1735080681
                            }
                        }
                    ],
                    "accuracy_rate": 0.92,
                    "difficulty_score": 0.3,
                    "avg_time_spent": 108248,
                    "tags": "шПц44фККхщ?,
                    "ai_tags": "цІччхКцЌцЇшДЈ,фКфЛЖчхГчГЛфИшПчЎ"
                },
                {
                    "id": 18598,
                    "subject_id": 3,
                    "chapter_id": 265,
                    "question_id": "5a1918e0-437f-46d4-8630-cbd7eaf4a0d7",
                    "difficulty": "Easy",
                    "answer": "1",
                    "question_type": 1,
                    "question": "шЎОфКфЛ?$A, B$ чцІчххЋфИК $\\frac{1}{3}, \\frac{1}{2}$, х?(1) хН?$A$ фИ?$B$ фКцЅц? (2)хН?$P(A B)=\\frac{1}{8}$ ц? $P(\\bar{A} B)$ чхМххЋфИК ().",
                    "analysis": "(1) х фИК $A$ фИ?$B$ фКцЅ, ц?$B \\subset \\bar{A}$, цфЛЅц $B=B \\bar{A}$, х?$P(\\bar{A} B)=P(B)=\\frac{1}{2}$.\n(2) $P(\\bar{A} B)=P(B-A B)=P(B)-P(A B)=\\frac{1}{2}-\\frac{1}{8}=\\frac{3}{8}$.",
                    "question_render_type": 1,
                    "analysis_render_type": 1,
                    "created_at": {
                        "seconds": 1764338559
                    },
                    "question_json": "mathreact/bec0141c7fcc4ed7a4f7ce4567eebccb",
                    "updated_at": {
                        "seconds": 1775673114
                    },
                    "version": 3,
                    "is_active_version": true,
                    "choices": [
                        {
                            "id": 83350,
                            "question_id": 18598,
                            "is_answer": true,
                            "choice": "$\\left(\\frac{1}{2}, \\frac{3}{8}\\right)$",
                            "choice_render_type": 1,
                            "choice_id": "1",
                            "created_at": {
                                "seconds": 1735080681
                            },
                            "updated_at": {
                                "seconds": 1735080681
                            }
                        },
                        {
                            "id": 83351,
                            "question_id": 18598,
                            "is_answer": false,
                            "choice": "$\\left(\\frac{1}{2}, \\frac{5}{8}\\right)$",
                            "choice_render_type": 1,
                            "choice_id": "2",
                            "created_at": {
                                "seconds": 1735080681
                            },
                            "updated_at": {
                                "seconds": 1735080681
                            }
                        },
                        {
                            "id": 83352,
                            "question_id": 18598,
                            "is_answer": false,
                            "choice": "$\\left(\\frac{5}{8}, \\frac{1}{2}\\right)$",
                            "choice_render_type": 1,
                            "choice_id": "3",
                            "created_at": {
                                "seconds": 1735080681
                            },
                            "updated_at": {
                                "seconds": 1735080681
                            }
                        },
                        {
                            "id": 83353,
                            "question_id": 18598,
                            "is_answer": false,
                            "choice": "$\\left(\\frac{3}{8}, \\frac{1}{2}\\right)$",
                            "choice_render_type": 1,
                            "choice_id": "4",
                            "created_at": {
                                "seconds": 1735080681
                            },
                            "updated_at": {
                                "seconds": 1735080681
                            }
                        }
                    ],
                    "accuracy_rate": 0.95,
                    "difficulty_score": 0.23,
                    "avg_time_spent": 87988,
                    "ai_tags": "фКфЛЖчцІч?фКцЅфКфЛЖ"
                },
                {
                    "id": 18601,
                    "subject_id": 3,
                    "chapter_id": 265,
                    "question_id": "ae5b8afa-f788-41ba-a265-f54b518e9f51",
                    "difficulty": "Easy",
                    "answer": "1",
                    "question_type": 1,
                    "question": "хЗВчЅ $P(A)=0.7, P(A-B)=0.3$, х?$P(\\overline{A B})=()$.",
                    "analysis": "ч?$P(A-B)=P(A)-P(AB)$яМхО $P(AB)=P(A)-P(A-B)=0.7-0.3=0.4$яМх $P(\\overline{AB})=1-P(AB)=1-0.4=0.6$у?,
                    "question_render_type": 1,
                    "analysis_render_type": 1,
                    "created_at": {
                        "seconds": 1764338565
                    },
                    "question_json": "mathreact/7e60f7dc04664b248fc37963e815c510",
                    "updated_at": {
                        "seconds": 1775673118
                    },
                    "version": 3,
                    "is_active_version": true,
                    "choices": [
                        {
                            "id": 83371,
                            "question_id": 18601,
                            "is_answer": true,
                            "choice": "$0.6$",
                            "choice_render_type": 1,
                            "choice_id": "1",
                            "created_at": {
                                "seconds": 1735080681
                            },
                            "updated_at": {
                                "seconds": 1735080681
                            }
                        },
                        {
                            "id": 83372,
                            "question_id": 18601,
                            "is_answer": false,
                            "choice": "$0.7$",
                            "choice_render_type": 1,
                            "choice_id": "2",
                            "created_at": {
                                "seconds": 1735080681
                            },
                            "updated_at": {
                                "seconds": 1735080681
                            }
                        },
                        {
                            "id": 83373,
                            "question_id": 18601,
                            "is_answer": false,
                            "choice": "$0.4$",
                            "choice_render_type": 1,
                            "choice_id": "3",
                            "created_at": {
                                "seconds": 1735080681
                            },
                            "updated_at": {
                                "seconds": 1735080681
                            }
                        },
                        {
                            "id": 83374,
                            "question_id": 18601,
                            "is_answer": false,
                            "choice": "$0.3$",
                            "choice_render_type": 1,
                            "choice_id": "4",
                            "created_at": {
                                "seconds": 1735080681
                            },
                            "updated_at": {
                                "seconds": 1735080681
                            }
                        }
                    ],
                    "accuracy_rate": 0.9,
                    "difficulty_score": 0.24,
                    "avg_time_spent": 123917,
                    "tags": "шПццщ,шПц51фККхщ?,
                    "ai_tags": "цІччхКцЌцЇшДЈ,хЏЙчЋфКфЛЖ"
                },
                {
                    "id": 18603,
                    "subject_id": 3,
                    "chapter_id": 265,
                    "question_id": "f643b263-d6ee-4ae3-addb-323497bbcdf9",
                    "difficulty": "Easy",
                    "answer": "1",
                    "question_type": 1,
                    "question": "шЎ?$P(A \\cup B)=a, P(\\bar{A})=b, P(\\bar{B})=c$, х?$P(A\\bar{B})$ ч­фК ( ).",
                    "analysis": "чБхЏЙхЖхОхЏчЅ $\\overline{A \\cup B}=\\bar{A} \\bar{B}$, цфЛ?$P(\\bar{A} \\bar{B})=1-P(A \\cup B)=1-a$. хчБфК?$\\bar{B}=(\\bar{A} \\bar{B}) \\cup(A \\bar{B})$, фИ?$(\\bar{A} \\bar{B}) \\cap(A \\bar{B})=\\varnothing$, цфЛ?$P(A \\bar{B})=P(\\bar{B})-P(\\bar{A} \\bar{B})=c-(1-a)=a+c-1$.",
                    "question_render_type": 1,
                    "analysis_render_type": 1,
                    "created_at": {
                        "seconds": 1764338568
                    },
                    "question_json": "mathreact/71b6c99234c242b9ab2b3cfdae78de14",
                    "updated_at": {
                        "seconds": 1775673113
                    },
                    "version": 3,
                    "is_active_version": true,
                    "choices": [
                        {
                            "id": 83385,
                            "question_id": 18603,
                            "is_answer": true,
                            "choice": "$a+c-1$",
                            "choice_render_type": 1,
                            "choice_id": "1",
                            "created_at": {
                                "seconds": 1735080681
                            },
                            "updated_at": {
                                "seconds": 1735080681
                            }
                        },
                        {
                            "id": 83386,
                            "question_id": 18603,
                            "is_answer": false,
                            "choice": "$(a+b) c$",
                            "choice_render_type": 1,
                            "choice_id": "2",
                            "created_at": {
                                "seconds": 1735080681
                            },
                            "updated_at": {
                                "seconds": 1735080681
                            }
                        },
                        {
                            "id": 83387,
                            "question_id": 18603,
                            "is_answer": false,
                            "choice": "$a-b-c$",
                            "choice_render_type": 1,
                            "choice_id": "3",
                            "created_at": {
                                "seconds": 1735080681
                            },
                            "updated_at": {
                                "seconds": 1735080681
                            }
                        },
                        {
                            "id": 83388,
                            "question_id": 18603,
                            "is_answer": false,
                            "choice": "$(1-b) c$",
                            "choice_render_type": 1,
                            "choice_id": "4",
                            "created_at": {
                                "seconds": 1735080681
                            },
                            "updated_at": {
                                "seconds": 1735080681
                            }
                        }
                    ],
                    "accuracy_rate": 0.91,
                    "difficulty_score": 0.24,
                    "avg_time_spent": 154679,
                    "tags": "шПц43фККхщ?,
                    "ai_tags": "цІччхКцЌцЇшДЈ,фКфЛЖчшПчЎ?
                },
                {
                    "id": 18604,
                    "subject_id": 3,
                    "chapter_id": 265,
                    "question_id": "c6f00151-03cf-417f-8d90-3e4510e93cef",
                    "difficulty": "Easy",
                    "answer": "1",
                    "question_type": 1,
                    "question": "шЎОфИЄфИЊщцКфКфЛ?$A, B$ цЛЁшЖГ $P(AB)=P(\\bar{A}\\bar{B})$яМфИ $P(A)=0.6$яМх $P(B)=(\\quad)$у?,
                    "analysis": "чБфК\n$$\n\\begin{aligned}\nP(AB) &= P(\\bar{A}\\bar{B}) = P(\\overline{A \\cup B}) = 1 - P(A \\cup B) \\\\\n&= 1 - [P(A) + P(B) - P(AB)] \\\\\n&= 1 - P(A) - P(B) + P(AB)\n\\end{aligned}\n$$\nцфЛ?$P(A)+P(B)=1$яМхА $P(A)=0.6$ фЛЃхЅяМхО $P(B)=1-P(A)=0.4$у?,
                    "question_render_type": 1,
                    "analysis_render_type": 1,
                    "created_at": {
                        "seconds": 1764338568
                    },
                    "question_json": "mathreact/fdef6662f8714fbdb41f673305beefad",
                    "updated_at": {
                        "seconds": 1775673116
                    },
                    "version": 3,
                    "is_active_version": true,
                    "choices": [
                        {
                            "id": 83392,
                            "question_id": 18604,
                            "is_answer": true,
                            "choice": "$0.4$",
                            "choice_render_type": 1,
                            "choice_id": "1",
                            "created_at": {
                                "seconds": 1735080681
                            },
                            "updated_at": {
                                "seconds": 1735080681
                            }
                        },
                        {
                            "id": 83393,
                            "question_id": 18604,
                            "is_answer": false,
                            "choice": "$0.5$",
                            "choice_render_type": 1,
                            "choice_id": "2",
                            "created_at": {
                                "seconds": 1735080681
                            },
                            "updated_at": {
                                "seconds": 1735080681
                            }
                        },
                        {
                            "id": 83394,
                            "question_id": 18604,
                            "is_answer": false,
                            "choice": "$0.6$",
                            "choice_render_type": 1,
                            "choice_id": "3",
                            "created_at": {
                                "seconds": 1735080681
                            },
                            "updated_at": {
                                "seconds": 1735080681
                            }
                        },
                        {
                            "id": 83395,
                            "question_id": 18604,
                            "is_answer": false,
                            "choice": "$0.7$",
                            "choice_render_type": 1,
                            "choice_id": "4",
                            "created_at": {
                                "seconds": 1735080681
                            },
                            "updated_at": {
                                "seconds": 1735080681
                            }
                        }
                    ],
                    "accuracy_rate": 0.91,
                    "difficulty_score": 0.26,
                    "avg_time_spent": 116475,
                    "ai_tags": "цІчшЎ?щцКфКфЛЖ,цІччхКцЌцЇшДЈ"
                },
                {
                    "id": 18605,
                    "subject_id": 3,
                    "chapter_id": 265,
                    "question_id": "e9624f8e-5d28-4788-a373-49bd7dceee2f",
                    "difficulty": "Easy",
                    "answer": "1",
                    "question_type": 1,
                    "question": "шЎОфИЄфИЊщцКфКфЛ?$A, B$ фКфИчИхЎЙ, фИ?$P(A)=0.4, P(B)=0.3$, х?$P(\\bar{A} \\bar{B})=(\\quad)$.",
                    "analysis": "ц ЙцЎцІччцЇшДЈц? $P(\\bar{A} \\bar{B})=P(\\overline{A \\cup B})=1-P(A \\cup B)=1-P(A)-P(B)+P(A B)$, х фИК $A$ фИ?$B$ фКфИчИхЎЙ, цфЛ?$P(A B)=0$, ц?$P(\\bar{A} \\bar{B})=1-0.4-0.3=0.3$.",
                    "question_render_type": 1,
                    "analysis_render_type": 1,
                    "created_at": {
                        "seconds": 1764338569
                    },
                    "question_json": "mathreact/ec999c4861624a01ac89675defb9a4ec",
                    "updated_at": {
                        "seconds": 1775673113
                    },
                    "version": 3,
                    "is_active_version": true,
                    "choices": [
                        {
                            "id": 83399,
                            "question_id": 18605,
                            "is_answer": true,
                            "choice": "$0.3$",
                            "choice_render_type": 1,
                            "choice_id": "1",
                            "created_at": {
                                "seconds": 1735080681
                            },
                            "updated_at": {
                                "seconds": 1735080681
                            }
                        },
                        {
                            "id": 83400,
                            "question_id": 18605,
                            "is_answer": false,
                            "choice": "$0.4$",
                            "choice_render_type": 1,
                            "choice_id": "2",
                            "created_at": {
                                "seconds": 1735080681
                            },
                            "updated_at": {
                                "seconds": 1735080681
                            }
                        },
                        {
                            "id": 83401,
                            "question_id": 18605,
                            "is_answer": false,
                            "choice": "$0.6$",
                            "choice_render_type": 1,
                            "choice_id": "3",
                            "created_at": {
                                "seconds": 1735080681
                            },
                            "updated_at": {
                                "seconds": 1735080681
                            }
                        },
                        {
                            "id": 83402,
                            "question_id": 18605,
                            "is_answer": false,
                            "choice": "$0.7$",
                            "choice_render_type": 1,
                            "choice_id": "4",
                            "created_at": {
                                "seconds": 1735080681
                            },
                            "updated_at": {
                                "seconds": 1735080681
                            }
                        }
                    ],
                    "accuracy_rate": 0.93,
                    "difficulty_score": 0.24,
                    "avg_time_spent": 69355,
                    "tags": "шПц34фККхщ?,
                    "ai_tags": "цІчшЎ?щцКфКфЛЖ,фКфИчИхЎЙ"
                },
                {
                    "id": 18608,
                    "subject_id": 3,
                    "chapter_id": 265,
                    "question_id": "bc33ab03-ab83-47bc-925f-f9384bad1c64",
                    "difficulty": "Easy",
                    "answer": "1",
                    "question_type": 1,
                    "question": "хЗВчЅ $P(\\bar{A})=0.5, P(\\bar{A} B)=0.2, P(B)=0.4$, хфИхшЏДцГфИц­ЃчЁЎчцЏ ( ).",
                    "analysis": "(1) х фИК $A B+\\bar{A} B=B$, фИ?$A B$ фИ?$\\bar{A} B$ цЏфИчИхЎЙч? цц $P(A B)+P(\\bar{A} B)=P(B)$, фКцЏ $P(A B)=P(B)-P(\\bar{A} B)=0.4-0.2=0.2$;\n(2) $P(A)=1-P(\\bar{A})=1-0.5=0.5, P(A-B)=P(A)-P(A B)=0.5-0.2=0.3$;\n(3) $P(A \\cup B)=P(A)+P(B)-P(A B)=0.5+0.4-0.2=0.7$;\n(4) $P(\\bar{A} \\bar{B})=P(\\overline{A \\cup B})=1-P(A \\cup B)=1-0.7=0.3$.",
                    "question_render_type": 1,
                    "analysis_render_type": 1,
                    "created_at": {
                        "seconds": 1764338582
                    },
                    "question_json": "mathreact/220da6bb3f2942ea80fd08d8ee28ef5b",
                    "updated_at": {
                        "seconds": 1775673116
                    },
                    "version": 3,
                    "is_active_version": true,
                    "choices": [
                        {
                            "id": 83420,
                            "question_id": 18608,
                            "is_answer": true,
                            "choice": "$P(A \\cup B)=0.4$",
                            "choice_render_type": 1,
                            "choice_id": "1",
                            "created_at": {
                                "seconds": 1735080681
                            },
                            "updated_at": {
                                "seconds": 1735080681
                            }
                        },
                        {
                            "id": 83421,
                            "question_id": 18608,
                            "is_answer": false,
                            "choice": "$P(A B)=0.2$",
                            "choice_render_type": 1,
                            "choice_id": "2",
                            "created_at": {
                                "seconds": 1735080681
                            },
                            "updated_at": {
                                "seconds": 1735080681
                            }
                        },
                        {
                            "id": 83422,
                            "question_id": 18608,
                            "is_answer": false,
                            "choice": "$P(A-B)=0.3$",
                            "choice_render_type": 1,
                            "choice_id": "3",
                            "created_at": {
                                "seconds": 1735080681
                            },
                            "updated_at": {
                                "seconds": 1735080681
                            }
                        },
                        {
                            "id": 83423,
                            "question_id": 18608,
                            "is_answer": false,
                            "choice": "$P(\\bar{A} \\bar{B})=0.3$",
                            "choice_render_type": 1,
                            "choice_id": "4",
                            "created_at": {
                                "seconds": 1735080681
                            },
                            "updated_at": {
                                "seconds": 1735080681
                            }
                        }
                    ],
                    "accuracy_rate": 0.88,
                    "difficulty_score": 0.23,
                    "avg_time_spent": 96153,
                    "ai_tags": "цІччхКцЌцЇшДЈ,фКфЛЖчшПчЎ?
                },
                {
                    "id": 18611,
                    "subject_id": 3,
                    "chapter_id": 265,
                    "question_id": "b4bb5a2b-bc9a-4772-a49c-bf809c1c2a49",
                    "difficulty": "Easy",
                    "answer": "1",
                    "question_type": 1,
                    "question": "шЎОфКфЛ?$A, B$ чЌчЋ, $P(\\bar{A} \\bar{B})=\\frac{1}{9}, P(A \\bar{B})=P(\\bar{A} B)$, х?$P(A)=(\\quad)$.",
                    "analysis": "чБфКфЛ?$A, B$ чЌчЋ $\\Rightarrow \\bar{A}, \\bar{B}$ чЌчЋ, $A, \\bar{B}$ чЌчЋ, $\\bar{A}, B$ чЌчЋ; шх\n$$\n\\left.\\begin{array}{c}\nP(\\bar{A} \\bar{B})=P(\\bar{A}) \\cdot P(\\bar{B})=\\frac{1}{9} \\\\\nP(A \\bar{B})=P(\\bar{A} B) \\\\\n\\Rightarrow P(A) \\cdot P(\\bar{B})=P(\\bar{A}) \\cdot P(B) \\\\\n\\Rightarrow P(\\bar{A})=P(\\bar{B})\n\\end{array}\\right\\} \\Rightarrow P(\\bar{A})=\\frac{1}{3} \\Rightarrow P(A)=\\frac{2}{3}\n$$",
                    "question_render_type": 1,
                    "analysis_render_type": 1,
                    "created_at": {
                        "seconds": 1764338589
                    },
                    "question_json": "mathreact/89d31f03bd6e4b4498b0476462ef07dd",
                    "updated_at": {
                        "seconds": 1775673115
                    },
                    "version": 3,
                    "is_active_version": true,
                    "choices": [
                        {
                            "id": 83441,
                            "question_id": 18611,
                            "is_answer": true,
                            "choice": "$\\frac{2}{3}$",
                            "choice_render_type": 1,
                            "choice_id": "1",
                            "created_at": {
                                "seconds": 1735080681
                            },
                            "updated_at": {
                                "seconds": 1735080681
                            }
                        },
                        {
                            "id": 83442,
                            "question_id": 18611,
                            "is_answer": false,
                            "choice": "$\\frac{1}{3}$",
                            "choice_render_type": 1,
                            "choice_id": "2",
                            "created_at": {
                                "seconds": 1735080681
                            },
                            "updated_at": {
                                "seconds": 1735080681
                            }
                        },
                        {
                            "id": 83443,
                            "question_id": 18611,
                            "is_answer": false,
                            "choice": "$\\frac{1}{2}$",
                            "choice_render_type": 1,
                            "choice_id": "3",
                            "created_at": {
                                "seconds": 1735080681
                            },
                            "updated_at": {
                                "seconds": 1735080681
                            }
                        },
                        {
                            "id": 83444,
                            "question_id": 18611,
                            "is_answer": false,
                            "choice": "$\\frac{1}{6}$",
                            "choice_render_type": 1,
                            "choice_id": "4",
                            "created_at": {
                                "seconds": 1735080681
                            },
                            "updated_at": {
                                "seconds": 1735080681
                            }
                        }
                    ],
                    "accuracy_rate": 0.81,
                    "difficulty_score": 0.31,
                    "avg_time_spent": 135512,
                    "tags": "шПццщ,шПц88фККхщ?,
                    "ai_tags": "фКфЛЖчЌчЋц?цІчшЎЁчЎ"
                },
                {
                    "id": 18612,
                    "subject_id": 3,
                    "chapter_id": 265,
                    "question_id": "bc2e7f77-6db2-437e-bcaa-e48a23e1230e",
                    "difficulty": "Easy",
                    "answer": "1",
                    "question_type": 1,
                    "question": "шЎ?$P(A)=p, P(B)=q, P(A \\cup B)=r$, х?$P(A \\bar{B}), P(\\bar{A} \\cdot \\bar{B}), P(\\bar{A} \\cup \\bar{B}), P(A \\cup \\bar{B})$ чхМххЋфИК ( ).",
                    "analysis": "фОщЂцц\n$$\nP(AB)=P(A)+P(B)-P(A \\cup B)=p+q-r\n$$\nфКцЏ\n$$\n\\begin{aligned}\n& P(A \\bar{B})=P(A)-P(AB)=p-(p+q-r)=r-q; \\\\\n& P(\\bar{A} \\bar{B})=P(\\overline{A \\cup B})=1-P(A \\cup B)=1-r; \\\\\n& P(\\bar{A} \\cup \\bar{B})=P(\\overline{AB})=1-P(AB)=1-(p+q-r)=1-p-q+r;\n\\end{aligned}\n$$\nх?$P(\\bar{A} B)=P(B)-P(AB)=q-(p+q-r)=r-p$, цфЛЅ\n$$\nP(A \\cup \\bar{B}) = P(\\overline{\\bar{A} B})=1-P(\\bar{A} B) = 1-(r-p)=1+p-r\n$$",
                    "question_render_type": 1,
                    "analysis_render_type": 1,
                    "created_at": {
                        "seconds": 1764338595
                    },
                    "question_json": "mathreact/e817b0df360647f594a7aa2aef821bf1",
                    "updated_at": {
                        "seconds": 1775673112
                    },
                    "version": 3,
                    "is_active_version": true,
                    "choices": [
                        {
                            "id": 83448,
                            "question_id": 18612,
                            "is_answer": true,
                            "choice": "$r-q, \\quad 1-r, \\quad 1+r-p-q, \\quad 1+p-r$",
                            "choice_render_type": 1,
                            "choice_id": "1",
                            "created_at": {
                                "seconds": 1735080681
                            },
                            "updated_at": {
                                "seconds": 1735080681
                            }
                        },
                        {
                            "id": 83449,
                            "question_id": 18612,
                            "is_answer": false,
                            "choice": "$r-p, \\quad 1-r, \\quad 1+r-p-q, \\quad 1+q-r$",
                            "choice_render_type": 1,
                            "choice_id": "2",
                            "created_at": {
                                "seconds": 1735080681
                            },
                            "updated_at": {
                                "seconds": 1735080681
                            }
                        },
                        {
                            "id": 83450,
                            "question_id": 18612,
                            "is_answer": false,
                            "choice": "$r-p, \\quad 1-r, \\quad 1+r-p-q, \\quad 1+p-r$",
                            "choice_render_type": 1,
                            "choice_id": "3",
                            "created_at": {
                                "seconds": 1735080681
                            },
                            "updated_at": {
                                "seconds": 1735080681
                            }
                        },
                        {
                            "id": 83451,
                            "question_id": 18612,
                            "is_answer": false,
                            "choice": "$r-q, \\quad 1-r, \\quad 1+r-p-q, \\quad 1+q-r$",
                            "choice_render_type": 1,
                            "choice_id": "4",
                            "created_at": {
                                "seconds": 1735080681
                            },
                            "updated_at": {
                                "seconds": 1735080681
                            }
                        }
                    ],
                    "accuracy_rate": 0.78,
                    "difficulty_score": 0.3,
                    "avg_time_spent": 352665,
                    "ai_tags": "цІчшЎЁчЎ,фКфЛЖшПчЎ"
                },
                {
                    "id": 18613,
                    "subject_id": 3,
                    "chapter_id": 265,
                    "question_id": "5b6227b5-2be0-40f6-862b-e7ce0493aec7",
                    "difficulty": "Easy",
                    "answer": "1",
                    "question_type": 1,
                    "question": "шЎОфКфЛ?$A, B$ фЛхчфИфИЊчцІчфИ?0.3 , фИ?$P(A)+P(B)=0.5$. х?$A, B$ шГхАцфИфИЊфИхччцІчфИК ().",
                    "analysis": "шшщшПщфКфЛЖцБшЇЃяМ $A, B$ шГхАцфИфИЊфИхччщфКфЛЖцЏ $A, B$ щНхчяМх?$AB$ учБфКфКфЛ?$A, B$ фЛхчфИфИЊчцІчфИ?0.3 яМхГ $P(A \\bar{B})+P(\\bar{A} B)=0.3$ яМ\nх?$P(A)-P(AB)+P(B)-P(AB)=0.3$ яМ\nцДчхО?$P(A)+P(B)-2 P(AB)=0.3$ яМ\nхц $P(A)+P(B)=0.5$ яМх $P(AB)=0.1$ у\nцфЛ?$A, B$ шГхАцфИфИЊфИхччцІч?$P(\\bar{A} \\cup \\bar{B})=P(\\overline{AB})=1-P(AB)=0.9$ у?,
                    "question_render_type": 1,
                    "analysis_render_type": 1,
                    "created_at": {
                        "seconds": 1764338600
                    },
                    "question_json": "mathreact/141f7dd09c9a492b92ac7c45057c8e38",
                    "updated_at": {
                        "seconds": 1775673112
                    },
                    "version": 3,
                    "is_active_version": true,
                    "choices": [
                        {
                            "id": 83455,
                            "question_id": 18613,
                            "is_answer": true,
                            "choice": "$0.9$",
                            "choice_render_type": 1,
                            "choice_id": "1",
                            "created_at": {
                                "seconds": 1735080681
                            },
                            "updated_at": {
                                "seconds": 1735080681
                            }
                        },
                        {
                            "id": 83456,
                            "question_id": 18613,
                            "is_answer": false,
                            "choice": "$0.8$",
                            "choice_render_type": 1,
                            "choice_id": "2",
                            "created_at": {
                                "seconds": 1735080681
                            },
                            "updated_at": {
                                "seconds": 1735080681
                            }
                        },
                        {
                            "id": 83457,
                            "question_id": 18613,
                            "is_answer": false,
                            "choice": "$0.2$",
                            "choice_render_type": 1,
                            "choice_id": "3",
                            "created_at": {
                                "seconds": 1735080681
                            },
                            "updated_at": {
                                "seconds": 1735080681
                            }
                        },
                        {
                            "id": 83458,
                            "question_id": 18613,
                            "is_answer": false,
                            "choice": "$0.1$",
                            "choice_render_type": 1,
                            "choice_id": "4",
                            "created_at": {
                                "seconds": 1735080681
                            },
                            "updated_at": {
                                "seconds": 1735080681
                            }
                        }
                    ],
                    "accuracy_rate": 0.57,
                    "difficulty_score": 0.46,
                    "avg_time_spent": 129069,
                    "ai_tags": "цІччхКцЌцЇшДЈ,щфКфЛ?
                }
            ]
        }
    },
    {
        "code": 200,
        "message": "OK",
        "data": {
            "total": 22,
            "questions": [
                {
                    "id": 18615,
                    "subject_id": 3,
                    "chapter_id": 265,
                    "question_id": "b4355c98-7106-4ad1-9e2b-10968418d64c",
                    "difficulty": "Easy",
                    "answer": "1",
                    "question_type": 1,
                    "question": "хЗВчЅ $A, B$ фИЄфИЊфКфЛЖцЛЁшЖГ $P(AB)=P(\\overline{A} \\overline{B})$, фИ?$P(A)=p$, х?$P(B)=(\\quad)$.",
                    "analysis": "цЎхЏЙхЖхОхцІччцЇшДЈц\n$$\nP(\\overline{A} \\overline{B})=P(\\overline{A \\cup B})=1-P(A \\cup B)=1-[P(A)+P(B)-P(AB)]=1-P(A)-P(B)+P(AB)\n$$\nчБщЂшЎОцЁфЛ?$P(AB)=P(\\overline{A} \\overline{B})$, хО\n$$\nP(AB)=1-P(A)-P(B)+P(AB)\n$$\nх?$P(A)+P(B)=1$. хчБ $P(A)=p$, хО?$P(B)=1-p$.",
                    "question_render_type": 1,
                    "analysis_render_type": 1,
                    "created_at": {
                        "seconds": 1764338605
                    },
                    "question_json": "mathreact/596133ca92d34095824ee5295b97f0e9",
                    "updated_at": {
                        "seconds": 1775673120
                    },
                    "version": 3,
                    "is_active_version": true,
                    "choices": [
                        {
                            "id": 83469,
                            "question_id": 18615,
                            "is_answer": true,
                            "choice": "$1-p$",
                            "choice_render_type": 1,
                            "choice_id": "1",
                            "created_at": {
                                "seconds": 1735080681
                            },
                            "updated_at": {
                                "seconds": 1735080681
                            }
                        },
                        {
                            "id": 83470,
                            "question_id": 18615,
                            "is_answer": false,
                            "choice": "$p$",
                            "choice_render_type": 1,
                            "choice_id": "2",
                            "created_at": {
                                "seconds": 1735080681
                            },
                            "updated_at": {
                                "seconds": 1735080681
                            }
                        },
                        {
                            "id": 83471,
                            "question_id": 18615,
                            "is_answer": false,
                            "choice": "$1-p^2$",
                            "choice_render_type": 1,
                            "choice_id": "3",
                            "created_at": {
                                "seconds": 1735080681
                            },
                            "updated_at": {
                                "seconds": 1735080681
                            }
                        },
                        {
                            "id": 83472,
                            "question_id": 18615,
                            "is_answer": false,
                            "choice": "$(1-p)^2$",
                            "choice_render_type": 1,
                            "choice_id": "4",
                            "created_at": {
                                "seconds": 1735080681
                            },
                            "updated_at": {
                                "seconds": 1735080681
                            }
                        }
                    ],
                    "accuracy_rate": 0.83,
                    "difficulty_score": 0.29,
                    "avg_time_spent": 132665,
                    "tags": "шПццщ,шПц78фККхщ?,
                    "ai_tags": "цІччхКцЌцЇшДЈ,хЏЙхЖхО?
                },
                {
                    "id": 18617,
                    "subject_id": 3,
                    "chapter_id": 265,
                    "question_id": "0cd9322c-242a-4a2c-9eef-686014533061",
                    "difficulty": "Easy",
                    "answer": "1",
                    "question_type": 1,
                    "question": "шЎОщцКфКфЛ?$A, B$ ххЖхфКфЛ?$A \\cup B$ чцІчххЋцЏ $0.4, 0.3$ х?$0.6$, ш?$\\bar{B}$ шЁЈчЄК $B$ чхЏЙчЋфКфЛ? щЃфЙчЇЏфКфЛ?$A \\bar{B}$ чцІч?$P(A \\bar{B})=(\\quad)$.",
                    "analysis": "х фИК $P(A \\cup B)=P(A)+P(B)-P(A B)$, х\n$$\nP(A \\bar{B})=P(A)-P(A B)=P(A \\cup B)-P(B)=0.6-0.3=0.3 .\n$$",
                    "question_render_type": 1,
                    "analysis_render_type": 1,
                    "created_at": {
                        "seconds": 1764338611
                    },
                    "question_json": "mathreact/e135625716fb4c34b7bf93718e68e76e",
                    "updated_at": {
                        "seconds": 1775673120
                    },
                    "version": 3,
                    "is_active_version": true,
                    "choices": [
                        {
                            "id": 83483,
                            "question_id": 18617,
                            "is_answer": true,
                            "choice": "$0.3$",
                            "choice_render_type": 1,
                            "choice_id": "1",
                            "created_at": {
                                "seconds": 1735080681
                            },
                            "updated_at": {
                                "seconds": 1735080681
                            }
                        },
                        {
                            "id": 83484,
                            "question_id": 18617,
                            "is_answer": false,
                            "choice": "$0.2$",
                            "choice_render_type": 1,
                            "choice_id": "2",
                            "created_at": {
                                "seconds": 1735080681
                            },
                            "updated_at": {
                                "seconds": 1735080681
                            }
                        },
                        {
                            "id": 83485,
                            "question_id": 18617,
                            "is_answer": false,
                            "choice": "$0.4$",
                            "choice_render_type": 1,
                            "choice_id": "3",
                            "created_at": {
                                "seconds": 1735080681
                            },
                            "updated_at": {
                                "seconds": 1735080681
                            }
                        },
                        {
                            "id": 83486,
                            "question_id": 18617,
                            "is_answer": false,
                            "choice": "$0.5$",
                            "choice_render_type": 1,
                            "choice_id": "4",
                            "created_at": {
                                "seconds": 1735080681
                            },
                            "updated_at": {
                                "seconds": 1735080681
                            }
                        }
                    ],
                    "accuracy_rate": 0.94,
                    "difficulty_score": 0.24,
                    "avg_time_spent": 96238,
                    "tags": "",
                    "ai_tags": "цІчшЎ?щцКфКфЛЖ,цІччх цГхЌхМ?
                }
            ]
        }
    }
]
